nornir_validate/__init__.py
nornir_validate/compliance_report.py
nornir_validate/core.py
nornir_validate/feature_templates/auth_session/auth_session_actual_state.py
nornir_validate/feature_templates/auth_session/auth_session_desired_state.j2
nornir_validate/feature_templates/evpn/evpn_actual_state.py
nornir_validate/feature_templates/evpn/evpn_desired_state.j2
nornir_validate/feature_templates/fhr/fhr_actual_state.py
nornir_validate/feature_templates/fhr/fhr_desired_state.j2
nornir_validate/feature_templates/fw/fw_actual_state.py
nornir_validate/feature_templates/fw/fw_desired_state.j2
nornir_validate/feature_templates/interface/interface_actual_state.py
nornir_validate/feature_templates/interface/interface_desired_state.j2
nornir_validate/feature_templates/intf_bonded/intf_bonded_actual_state.py
nornir_validate/feature_templates/intf_bonded/intf_bonded_desired_state.j2
nornir_validate/feature_templates/layer2/layer2_actual_state.py
nornir_validate/feature_templates/layer2/layer2_desired_state.j2
nornir_validate/feature_templates/neighbor/neighbor_actual_state.py
nornir_validate/feature_templates/neighbor/neighbor_desired_state.j2
nornir_validate/feature_templates/redundancy/redundancy_actual_state.py
nornir_validate/feature_templates/redundancy/redundancy_desired_state.j2
nornir_validate/feature_templates/route_protocol/route_protocol_actual_state.py
nornir_validate/feature_templates/route_protocol/route_protocol_desired_state.j2
nornir_validate/feature_templates/route_table/route_table_actual_state.py
nornir_validate/feature_templates/route_table/route_table_desired_state.j2
nornir_validate/feature_templates/sdwan/sdwan_actual_state.py
nornir_validate/feature_templates/sdwan/sdwan_desired_state.j2
nornir_validate/feature_templates/system/system_actual_state.py
nornir_validate/feature_templates/system/system_desired_state.j2
nornir_validate/feature_templates/vpn/vpn_actual_state.py
nornir_validate/feature_templates/vpn/vpn_desired_state.j2
nornir_validate-0.3.1.dist-info/WHEEL
nornir_validate-0.3.1.dist-info/METADATA
nornir_validate-0.3.1.dist-info/RECORD
