Metadata-Version: 2.4
Name: nornir-validate
Version: 0.3.1
Summary: Nornir plugin to validate network state on a per-device basis
License-Expression: MIT
Classifier: License :: OSI Approved :: MIT License
Classifier: Development Status :: 3 - Alpha
Classifier: Programming Language :: Python :: 3.12
Classifier: Programming Language :: Python :: 3.13
Classifier: Programming Language :: Python :: 3.14
Requires-Dist: napalm>=5.1.0
Requires-Dist: nornir-jinja2>=0.2.0
Requires-Dist: nornir-netmiko>=1.0.1
Requires-Dist: nornir-rich
Requires-Dist: nornir-utils>=0.2.0
Requires-Dist: ntc-templates
Requires-Dist: pyaml>=25.7.0
Requires-Dist: types-pyyaml>=6.0.12.20250915
Requires-Dist: ipdb>=0.13.13 ; extra == 'dev'
Requires-Dist: mypy>=1.18.2 ; extra == 'dev'
Requires-Dist: pytest>=8.4.2 ; extra == 'dev'
Requires-Dist: ruff>=0.14.4 ; extra == 'dev'
Requires-Dist: sphinx>=8.2.3 ; extra == 'docs'
Requires-Dist: sphinx-rtd-theme>=3.0.2 ; extra == 'docs'
Requires-Python: >=3.12
Project-URL: Homepage, https://github.com/sjhloco/nornir-validate
Project-URL: Issues, https://github.com/sjhloco/nornir-validate/issues
Project-URL: Repository, https://github.com/sjhloco/nornir-validate
Provides-Extra: dev
Provides-Extra: docs
